<?xml version="1.0" encoding="utf-8"?>
<!DOCTYPE documentInfo>
<documentInfo url="/home/duy/Downloads/sicp.pdf">
 <generalInfo>
  <history>
   <oldPage viewport="433;C2:0.499673:0.970168:1"/>
   <oldPage viewport="434;C2:0.499673:0.989892:1"/>
   <oldPage viewport="435;C2:0.499673:1.00074:1"/>
   <oldPage viewport="436;C2:0.499673:0.945513:1"/>
   <oldPage viewport="437;C2:0.499673:0.00320513:1"/>
   <oldPage viewport="436;C2:0.499673:0.997288:1"/>
   <oldPage viewport="437;C2:0.499673:0.0101085:1"/>
   <oldPage viewport="436;C2:0.499673:1.00222:1"/>
   <oldPage viewport="437;C2:0.499673:1.00123:1"/>
   <oldPage viewport="438;C2:0.499673:0.996302:1"/>
   <current viewport="439;C2:0.499673:0.649655:1"/>
  </history>
  <views>
   <view name="PageView">
    <zoom mode="0" value="1.85"/>
    <continuous mode="1"/>
    <viewMode mode="0"/>
    <trimMargins value="0"/>
   </view>
  </views>
 </generalInfo>
</documentInfo>
