<?xml version="1.0" encoding="utf-8"?>
<!DOCTYPE documentInfo>
<documentInfo url="/home/duy/Documents/Technical Analysis Explained - Martin Pring.pdf">
 <generalInfo>
  <history>
   <oldPage viewport="88"/>
   <oldPage viewport="87"/>
   <oldPage viewport="86"/>
   <oldPage viewport="85"/>
   <oldPage viewport="84"/>
   <oldPage viewport="83"/>
   <oldPage viewport="82"/>
   <oldPage viewport="81"/>
   <oldPage viewport="80"/>
   <oldPage viewport="79"/>
   <current viewport="81;C2:0.499737:0.397311:1"/>
  </history>
  <views>
   <view name="PageView">
    <zoom value="1.14603" mode="1"/>
    <continuous mode="1"/>
    <viewMode mode="0"/>
    <trimMargins value="0"/>
   </view>
  </views>
 </generalInfo>
</documentInfo>
